solo_django_admin/__init__.py
solo_django_admin/manage.py
solo_django_admin/models.py
solo_django_admin/core/__init__.py
solo_django_admin/core/asgi.py
solo_django_admin/core/settings.py
solo_django_admin/core/urls.py
solo_django_admin-0.1.5.dist-info/LICENSE
solo_django_admin-0.1.5.dist-info/METADATA
solo_django_admin-0.1.5.dist-info/WHEEL
solo_django_admin-0.1.5.dist-info/top_level.txt
solo_django_admin-0.1.5.dist-info/RECORD
