Metadata-Version: 2.1
Name: solo_django_admin
Version: 0.1.5
Summary: Django admin for non Django ORM
Home-page: https://github.com/xelaxela13/solo_django_admin.git
Author: Oleksii Stepanenko
Author-email: xelaxela13@gmail.com
Classifier: Programming Language :: Python :: 3
Classifier: License :: OSI Approved :: MIT License
Classifier: Operating System :: OS Independent
Requires-Python: >=3.6
License-File: LICENSE
Requires-Dist: Django>=4.2
Requires-Dist: python-dotenv>=1.0.0
Requires-Dist: tortoise-orm>=0.21.0
